dialup/__init__.py
dialup/main_denoiser.py
dialup/main_noiser.py
dialup/data/lexicons/acf-hat/acf-hat_functional.json
dialup/data/lexicons/acm-arb/acm-arb_functional.json
dialup/data/lexicons/acq-arb/acq-arb_functional.json
dialup/data/lexicons/aeb-arb/aeb-arb_functional.json
dialup/data/lexicons/ajp-arb/ajp-arb_functional.json
dialup/data/lexicons/apc-arb/apc-arb_functional.json
dialup/data/lexicons/ars-arb/ars-arb_functional.json
dialup/data/lexicons/ary-arb/ary-arb_functional.json
dialup/data/lexicons/arz-arb/arz-arb_functional.json
dialup/data/lexicons/ast-ita/ast-ita_functional.json
dialup/data/lexicons/awa-hin/awa-hin_functional.json
dialup/data/lexicons/azj-tur/azj-tur_functional.json
dialup/data/lexicons/bho-hin/bho-hin_functional.json
dialup/data/lexicons/cat-ita/cat-ita_functional.json
dialup/data/lexicons/ceb-ind/ceb-ind_functional.json
dialup/data/lexicons/crh-tur/crh-tur_functional.json
dialup/data/lexicons/crs-hat/crs-hat_functional.json
dialup/data/lexicons/fij-ind/fij-ind_functional.json
dialup/data/lexicons/fra-ita/fra-ita_functional.json
dialup/data/lexicons/fur-ita/fur-ita_functional.json
dialup/data/lexicons/glg-ita/glg-ita_functional.json
dialup/data/lexicons/hne-hin/hne-hin_functional.json
dialup/data/lexicons/ilo-ind/ilo-ind_functional.json
dialup/data/lexicons/ita-ita/ita-ita_functional.json
dialup/data/lexicons/jav-ind/jav-ind_functional.json
dialup/data/lexicons/lij-ita/lij-ita_functional.json
dialup/data/lexicons/lmo-ita/lmo-ita_functional.json
dialup/data/lexicons/mag-hin/mag-hin_functional.json
dialup/data/lexicons/mai-hin/mai-hin_functional.json
dialup/data/lexicons/mfe-hat/mfe-hat_functional.json
dialup/data/lexicons/mri-ind/mri-ind_functional.json
dialup/data/lexicons/oci-ita/oci-ita_functional.json
dialup/data/lexicons/pag-ind/pag-ind_functional.json
dialup/data/lexicons/plt-ind/plt-ind_functional.json
dialup/data/lexicons/por-ita/por-ita_functional.json
dialup/data/lexicons/ron-ita/ron-ita_functional.json
dialup-1.0.1.dist-info/licenses/LICENSE
dialup-1.0.1.dist-info/METADATA
dialup-1.0.1.dist-info/WHEEL
dialup-1.0.1.dist-info/top_level.txt
dialup-1.0.1.dist-info/RECORD
