Metadata-Version: 2.4
Name: dialup
Version: 1.0.1
Summary: DialUp! Generating linguistically plausible artificial dialects; preprocessing low-resource language inputs.
Author-email: Niyati Bafna <niyatibafna13@gmail.com>
License: MIT
Project-URL: Homepage, https://github.com/niyatibafna/dialup/tree/master/dialup_pkg
Project-URL: Issues, https://github.com/niyatibafna/dialup/issues
Requires-Python: >=3.9
License-File: LICENSE
Requires-Dist: numpy
Requires-Dist: scipy
Dynamic: license-file
